kedro_light/__init__.py
kedro_light/kedro.py
kedro_light/kedro_viz.py
kedro_light-2023.3.13.dist-info/LICENSE
kedro_light-2023.3.13.dist-info/METADATA
kedro_light-2023.3.13.dist-info/WHEEL
kedro_light-2023.3.13.dist-info/top_level.txt
kedro_light-2023.3.13.dist-info/RECORD
