Metadata-Version: 2.1
Name: kedro-light
Version: 2023.3.13
Summary: A lightweight interface to Kedro and Kedro-Viz
Author-email: Elliott Wise <ell.wise@gmail.com>
License: MIT License
Project-URL: source, https://github.com/ellwise/kedro-light
Project-URL: docs, https://ellwise.github.io/kedro-light
License-File: LICENSE
Requires-Dist: kedro
Requires-Dist: kedro-viz
Provides-Extra: api
Requires-Dist: kedro[api] ; extra == 'api'
Provides-Extra: biosequence
Requires-Dist: kedro[biosequence] ; extra == 'biosequence'
Provides-Extra: dask
Requires-Dist: kedro[dask] ; extra == 'dask'
Provides-Extra: dev
Requires-Dist: black ; extra == 'dev'
Requires-Dist: build ; extra == 'dev'
Requires-Dist: isort ; extra == 'dev'
Requires-Dist: mkdocs-material ; extra == 'dev'
Requires-Dist: pip-tools ; extra == 'dev'
Requires-Dist: ruff ; extra == 'dev'
Requires-Dist: twine ; extra == 'dev'
Provides-Extra: docs
Requires-Dist: kedro[docs] ; extra == 'docs'
Provides-Extra: geopandas
Requires-Dist: kedro[geopandas] ; extra == 'geopandas'
Provides-Extra: holoviews
Requires-Dist: kedro[holoviews] ; extra == 'holoviews'
Provides-Extra: matplotlib
Requires-Dist: kedro[matplotlib] ; extra == 'matplotlib'
Provides-Extra: networkx
Requires-Dist: kedro[networkx] ; extra == 'networkx'
Provides-Extra: pandas
Requires-Dist: kedro[pandas] ; extra == 'pandas'
Provides-Extra: pillow
Requires-Dist: kedro[pillow] ; extra == 'pillow'
Provides-Extra: plotly
Requires-Dist: kedro[plotly] ; extra == 'plotly'
Provides-Extra: redis
Requires-Dist: kedro[redis] ; extra == 'redis'
Provides-Extra: spark
Requires-Dist: kedro[spark] ; extra == 'spark'
Provides-Extra: tensorflow
Requires-Dist: kedro[tensorflow] ; extra == 'tensorflow'
Provides-Extra: yaml
Requires-Dist: kedro[yaml] ; extra == 'yaml'
